geo_features_generator/__init__.py
geo_features_generator/generator.py
geo_features_generator/utils.py
geo_features_generator-0.2.1.dist-info/METADATA
geo_features_generator-0.2.1.dist-info/WHEEL
geo_features_generator-0.2.1.dist-info/RECORD
