Metadata-Version: 2.4
Name: geo_features_generator
Version: 0.2.1
Summary: Sklearn-style generator of geo features: distances, angles, cosine similarity, KMeans, NN, polar features
Project-URL: Homepage, https://pypi.org/project/geo-features-generator/
Project-URL: Repository, https://github.com/sefixnep/geo_features_generator
Project-URL: Bug Tracker, https://github.com/sefixnep/geo_features_generator/issues
Author-email: sefixnep <rodionovs337@gmail.com>
License-Expression: MIT
Classifier: License :: OSI Approved :: MIT License
Classifier: Operating System :: OS Independent
Classifier: Programming Language :: Python :: 3
Classifier: Topic :: Scientific/Engineering :: GIS
Requires-Python: >=3.8
Requires-Dist: numpy>=1.20
Requires-Dist: pandas>=1.3
Provides-Extra: h3
Requires-Dist: h3>=4.0.0; extra == 'h3'
Provides-Extra: ml
Requires-Dist: scikit-learn>=1.1; extra == 'ml'
